pyrite/__init__.py
pyrite/game.py
pyrite/py.typed
pyrite/_helper/defaults.py
pyrite/core/display_settings.py
pyrite/core/entity_manager.py
pyrite/core/game_data.py
pyrite/core/rate_settings.py
pyrite/core/renderer.py
pyrite/types/__init__.py
pyrite/types/_base_type.py
pyrite/types/camera.py
pyrite/types/entity.py
pyrite/types/enums.py
pyrite/types/renderable.py
pyrite/types/static_decor.py
pyrite/types/surface_sector.py
pyrite/utils/__init__.py
pyrite/utils/performance/dazzler.py
pyrite/utils/performance/fps_tracker.py
pyrite_framework-0.12.1.dist-info/LICENSE
pyrite_framework-0.12.1.dist-info/METADATA
pyrite_framework-0.12.1.dist-info/WHEEL
pyrite_framework-0.12.1.dist-info/top_level.txt
pyrite_framework-0.12.1.dist-info/RECORD
