Metadata-Version: 2.2
Name: pyrite_framework
Version: 0.12.1
Summary: A simple yet featureful framework for simplifying pygame game creation.
Author-email: BetterBuiltFool <betterbuiltfool@gmail.com>
Classifier: Programming Language :: Python :: 3
Classifier: License :: OSI Approved :: MIT License
Classifier: Operating System :: OS Independent
Classifier: Topic :: Games/Entertainment
Classifier: Topic :: Software Development :: Libraries :: pygame
Classifier: Typing :: Typed
Requires-Python: >=3.12.4
License-File: LICENSE
Requires-Dist: pygame_ce>=2.5.2
